InfIK/InfIK.py
InfIK/__init__.py
InfIK-1.1.dist-info/LICENSE
InfIK-1.1.dist-info/METADATA
InfIK-1.1.dist-info/WHEEL
InfIK-1.1.dist-info/top_level.txt
InfIK-1.1.dist-info/RECORD
